yabu/__init__.py
yabu/__main__.py
yabu/backup_task.py
yabu/version.py
yabu/yabu.py
yabu/exceptions/__init__.py
yabu/log/__init__.py
yabu/resources/config.schema.yaml
yabu-0.1.3.3.data/data/config.example.yaml
yabu-0.1.3.3.data/data/yabu.service
yabu-0.1.3.3.data/data/yabu.timer
yabu-0.1.3.3.dist-info/LICENSE
yabu-0.1.3.3.dist-info/METADATA
yabu-0.1.3.3.dist-info/WHEEL
yabu-0.1.3.3.dist-info/entry_points.txt
yabu-0.1.3.3.dist-info/top_level.txt
yabu-0.1.3.3.dist-info/RECORD
